omzo_pkg/__init__.py
omzo_pkg/annee_bissextile.py
omzo_pkg/table_multiplication.py
omzo_pkg_oumar-1.0.0.dist-info/LICENSE
omzo_pkg_oumar-1.0.0.dist-info/METADATA
omzo_pkg_oumar-1.0.0.dist-info/WHEEL
omzo_pkg_oumar-1.0.0.dist-info/top_level.txt
omzo_pkg_oumar-1.0.0.dist-info/RECORD
