Metadata-Version: 2.1
Name: omzo-pkg-oumar
Version: 1.0.0
Summary: Mon premier projet
Home-page: 
Author: Oumar Dia
Author-email: oumardia8@gmail.com
License: UNKNOWN
Platform: UNKNOWN
Classifier: Programming Language :: Python :: 3.9
Classifier: License :: OSI Approved :: MIT License
Classifier: Operating System :: OS Independent
Requires-Python: >=3.6
